{
    "Title": "Night and the City",
    "Year": "1950",
    "Rated": "Not Rated",
    "Released": "27 Nov 1950",
    "Runtime": "96 min",
    "Genre": "Crime, Film-Noir, Mystery, Sport, Thriller",
    "Director": "Jules Dassin",
    "Writer": "Jo Eisinger (screenplay), Gerald Kersh (novel)",
    "Actors": "Richard Widmark, Gene Tierney, Googie Withers, Hugh Marlowe",
    "Plot": "A small-time grifter and nightclub tout takes advantage of some fortuitous circumstances and tries to become a big-time player as a wrestling promoter.",
    "Language": "English",
    "Country": "UK, USA",
    "Awards": "N/A",
    "Poster": "https://m.media-amazon.com/images/M/MV5BZTJlMDAyYTctYmY1NS00MWQ3LWIxZjgtZWM0OGRiNTExYTJjXkEyXkFqcGdeQXVyMjUxODE0MDY@._V1_SX300.jpg",
    "Ratings": [
        {
            "Source": "Internet Movie Database",
            "Value": "8.0/10"
        },
        {
            "Source": "Rotten Tomatoes",
            "Value": "79%"
        }
    ],
    "Metascore": "N/A",
    "imdbRating": "8.0",
    "imdbVotes": "10,762",
    "imdbID": "tt0042788",
    "Type": "movie",
    "DVD": "01 Feb 2005",
    "BoxOffice": "N/A",
    "Production": "Criterion Collection",
    "Website": "N/A",
    "Response": "True"
}