{
    "Title": "Two Mules for Sister Sara",
    "Year": "1970",
    "Rated": "GP",
    "Released": "16 Jun 1970",
    "Runtime": "116 min",
    "Genre": "Adventure, Romance, War, Western",
    "Director": "Don Siegel",
    "Writer": "Budd Boetticher (story), Albert Maltz (screenplay)",
    "Actors": "Shirley MacLaine, Clint Eastwood, Manolo F\u00e1bregas, Alberto Morin",
    "Plot": "Nun Sara (Shirley MacLaine) is on the run in Mexico and is saved from cowboys by Hogan (Clint Eastwood), who is preparing for a future mission to capture a French fort. The pair become good friends, but Sara never does tell him the true reason behind her being outlawed.",
    "Language": "English, Spanish, French, Latin",
    "Country": "Mexico, USA",
    "Awards": "2 nominations.",
    "Poster": "https://m.media-amazon.com/images/M/MV5BMGZiMzQyZjgtZTE0NC00MGQ0LWExZGMtMWUxZGU1OTVmMTg5XkEyXkFqcGdeQXVyNjc1NTYyMjg@._V1_SX300.jpg",
    "Ratings": [
        {
            "Source": "Internet Movie Database",
            "Value": "7.0/10"
        },
        {
            "Source": "Rotten Tomatoes",
            "Value": "64%"
        },
        {
            "Source": "Metacritic",
            "Value": "62/100"
        }
    ],
    "Metascore": "62",
    "imdbRating": "7.0",
    "imdbVotes": "21,797",
    "imdbID": "tt0065134",
    "Type": "movie",
    "DVD": "06 May 2003",
    "BoxOffice": "N/A",
    "Production": "Universal Studios",
    "Website": "N/A",
    "Response": "True"
}