{
    "Title": "The Lady from Shanghai",
    "Year": "1947",
    "Rated": "Not Rated",
    "Released": "14 Apr 1948",
    "Runtime": "87 min",
    "Genre": "Crime, Drama, Film-Noir, Mystery, Thriller",
    "Director": "Orson Welles",
    "Writer": "Sherwood King (story based on a novel by), Orson Welles (screenplay)",
    "Actors": "Rita Hayworth, Orson Welles, Everett Sloane, Glenn Anders",
    "Plot": "Fascinated by gorgeous Mrs. Bannister, seaman Michael O'Hara joins a bizarre yachting cruise, and ends up mired in a complex murder plot.",
    "Language": "English, Cantonese",
    "Country": "USA",
    "Awards": "N/A",
    "Poster": "https://m.media-amazon.com/images/M/MV5BNWZkNTYxZjQtN2IwZi00OGExLTg3ZDEtODNjMDFkN2Y5Y2NkL2ltYWdlL2ltYWdlXkEyXkFqcGdeQXVyNjc1NTYyMjg@._V1_SX300.jpg",
    "Ratings": [
        {
            "Source": "Internet Movie Database",
            "Value": "7.6/10"
        },
        {
            "Source": "Rotten Tomatoes",
            "Value": "82%"
        }
    ],
    "Metascore": "N/A",
    "imdbRating": "7.6",
    "imdbVotes": "24,010",
    "imdbID": "tt0040525",
    "Type": "movie",
    "DVD": "03 Oct 2000",
    "BoxOffice": "N/A",
    "Production": "Columbia Pictures Corporation",
    "Website": "N/A",
    "Response": "True"
}