{
    "Title": "The Tall Blond Man with One Black Shoe",
    "Year": "1972",
    "Rated": "PG",
    "Released": "30 Aug 1973",
    "Runtime": "90 min",
    "Genre": "Comedy, Mystery",
    "Director": "Yves Robert",
    "Writer": "Yves Robert (screenplay), Francis Veber (screenplay), Francis Veber (dialogue)",
    "Actors": "Pierre Richard, Bernard Blier, Jean Rochefort, Mireille Darc",
    "Plot": "A hapless orchestra player becomes an unwitting pawn of rival factions within the French secret service after he is chosen as a decoy by being identified as a super secret agent.",
    "Language": "French, English",
    "Country": "France",
    "Awards": "3 wins & 1 nomination.",
    "Poster": "https://m.media-amazon.com/images/M/MV5BYmIwY2U4ZTgtYjE4Mi00NGQxLTk3ZWQtMWY5YjU4ZGYwNGU3XkEyXkFqcGdeQXVyMjA0MzYwMDY@._V1_SX300.jpg",
    "Ratings": [
        {
            "Source": "Internet Movie Database",
            "Value": "7.3/10"
        }
    ],
    "Metascore": "N/A",
    "imdbRating": "7.3",
    "imdbVotes": "6,619",
    "imdbID": "tt0068655",
    "Type": "movie",
    "DVD": "07 Jul 2015",
    "BoxOffice": "N/A",
    "Production": "Gaumont",
    "Website": "N/A",
    "Response": "True"
}