{
    "Title": "Going Places",
    "Year": "1974",
    "Rated": "R",
    "Released": "13 May 1974",
    "Runtime": "117 min",
    "Genre": "Action, Comedy, Crime, Drama",
    "Director": "Bertrand Blier",
    "Writer": "Bertrand Blier (novel), Bertrand Blier (screenplay), Philippe Dumar\u00e7ay (screenplay)",
    "Actors": "G\u00e9rard Depardieu, Miou-Miou, Patrick Dewaere, Christian Alers",
    "Plot": "Two whimsical, aimless thugs harass and assault women, steal, murder, and alternately charm, fight, or sprint their way out of trouble. They take whatever the bourgeois characters value: ...",
    "Language": "French",
    "Country": "France",
    "Awards": "N/A",
    "Poster": "https://m.media-amazon.com/images/M/MV5BOGFkNjZmY2EtYzIxZi00Mzg0LTlmZjEtODc5ZDE5MDhjMGQ5XkEyXkFqcGdeQXVyMjI4MjA5MzA@._V1_SX300.jpg",
    "Ratings": [
        {
            "Source": "Internet Movie Database",
            "Value": "7.3/10"
        },
        {
            "Source": "Rotten Tomatoes",
            "Value": "80%"
        }
    ],
    "Metascore": "N/A",
    "imdbRating": "7.3",
    "imdbVotes": "7,572",
    "imdbID": "tt0072353",
    "Type": "movie",
    "DVD": "22 Jan 2002",
    "BoxOffice": "N/A",
    "Production": "Franco London Films",
    "Website": "N/A",
    "Response": "True"
}