{
    "Title": "Zardoz",
    "Year": "1974",
    "Rated": "R",
    "Released": "06 Feb 1974",
    "Runtime": "105 min",
    "Genre": "Adventure, Fantasy, Sci-Fi",
    "Director": "John Boorman",
    "Writer": "John Boorman",
    "Actors": "Sean Connery, Charlotte Rampling, Sara Kestelman, John Alderton",
    "Plot": "In the distant future, a savage trained only to kill finds a way into the community of bored immortals that alone preserves humanity's achievements.",
    "Language": "English, Italian, Swedish, Latin, German, French, Irish",
    "Country": "UK, USA",
    "Awards": "Nominated for 1 BAFTA Film Award. Another 1 nomination.",
    "Poster": "https://m.media-amazon.com/images/M/MV5BMDg5NTYzNzMtNzhmOS00NzEyLWJlMWMtMzUzNjdhYjY2NDI3XkEyXkFqcGdeQXVyNjUwMzI2NzU@._V1_SX300.jpg",
    "Ratings": [
        {
            "Source": "Internet Movie Database",
            "Value": "5.9/10"
        },
        {
            "Source": "Rotten Tomatoes",
            "Value": "48%"
        },
        {
            "Source": "Metacritic",
            "Value": "46/100"
        }
    ],
    "Metascore": "46",
    "imdbRating": "5.9",
    "imdbVotes": "18,025",
    "imdbID": "tt0070948",
    "Type": "movie",
    "DVD": "26 Mar 2001",
    "BoxOffice": "N/A",
    "Production": "Fox",
    "Website": "N/A",
    "Response": "True"
}