{
    "Title": "Ragtime",
    "Year": "1981",
    "Rated": "PG",
    "Released": "25 Dec 1981",
    "Runtime": "155 min",
    "Genre": "Drama",
    "Director": "Milos Forman",
    "Writer": "E.L. Doctorow (based on the novel by), Michael Weller (screenplay)",
    "Actors": "James Cagney, Brad Dourif, Moses Gunn, Elizabeth McGovern",
    "Plot": "A young black pianist becomes embroiled in the lives of an upper-class white family set among the racial tensions, infidelity, violence, and other nostalgic events in early 1900s New York City.",
    "Language": "English",
    "Country": "USA",
    "Awards": "Nominated for 8 Oscars. Another 2 wins & 13 nominations.",
    "Poster": "https://m.media-amazon.com/images/M/MV5BNDk0ZTQ3ODAtMjUwMi00YzQ2LTgyMDAtZWY4ZGIxNTRlYzIwXkEyXkFqcGdeQXVyNjQzNDI3NzY@._V1_SX300.jpg",
    "Ratings": [
        {
            "Source": "Internet Movie Database",
            "Value": "7.3/10"
        },
        {
            "Source": "Rotten Tomatoes",
            "Value": "91%"
        },
        {
            "Source": "Metacritic",
            "Value": "57/100"
        }
    ],
    "Metascore": "57",
    "imdbRating": "7.3",
    "imdbVotes": "8,022",
    "imdbID": "tt0082970",
    "Type": "movie",
    "DVD": "16 Nov 2004",
    "BoxOffice": "N/A",
    "Production": "Paramount Pictures",
    "Website": "N/A",
    "Response": "True"
}