{
    "Title": "The Last Waltz",
    "Year": "1978",
    "Rated": "PG",
    "Released": "26 Apr 1978",
    "Runtime": "117 min",
    "Genre": "Documentary, Music",
    "Director": "Martin Scorsese",
    "Writer": "Mardik Martin (treatment)",
    "Actors": "The Band, Rick Danko, Levon Helm, Garth Hudson",
    "Plot": "A film account and presentation of the final concert of The Band.",
    "Language": "English, Middle English",
    "Country": "USA",
    "Awards": "2 wins & 3 nominations.",
    "Poster": "https://m.media-amazon.com/images/M/MV5BODk2N2RkMGEtMGJjZS00OTk0LTk5NjgtNTg4ZjdiNDI2ZjE1XkEyXkFqcGdeQXVyMjUzOTY1NTc@._V1_SX300.jpg",
    "Ratings": [
        {
            "Source": "Internet Movie Database",
            "Value": "8.2/10"
        },
        {
            "Source": "Rotten Tomatoes",
            "Value": "98%"
        },
        {
            "Source": "Metacritic",
            "Value": "88/100"
        }
    ],
    "Metascore": "88",
    "imdbRating": "8.2",
    "imdbVotes": "14,716",
    "imdbID": "tt0077838",
    "Type": "movie",
    "DVD": "07 May 2002",
    "BoxOffice": "N/A",
    "Production": "MGM",
    "Website": "N/A",
    "Response": "True"
}