{
    "Title": "The Man Who Fell to Earth",
    "Year": "1976",
    "Rated": "R",
    "Released": "08 Apr 1976",
    "Runtime": "139 min",
    "Genre": "Drama, Sci-Fi",
    "Director": "Nicolas Roeg",
    "Writer": "Paul Mayersberg (screenplay), Walter Tevis (from the novel by)",
    "Actors": "David Bowie, Rip Torn, Candy Clark, Buck Henry",
    "Plot": "An alien must pose as a human to save his dying planet, but a woman and greed of other men create complications.",
    "Language": "English",
    "Country": "UK",
    "Awards": "1 win & 3 nominations.",
    "Poster": "https://m.media-amazon.com/images/M/MV5BOTVhM2JhZDAtYWMwMS00NjE5LWI5ZTEtNDQxZmIxMzIxYzVlXkEyXkFqcGdeQXVyNjc1NTYyMjg@._V1_SX300.jpg",
    "Ratings": [
        {
            "Source": "Internet Movie Database",
            "Value": "6.7/10"
        },
        {
            "Source": "Rotten Tomatoes",
            "Value": "83%"
        },
        {
            "Source": "Metacritic",
            "Value": "81/100"
        }
    ],
    "Metascore": "81",
    "imdbRating": "6.7",
    "imdbVotes": "22,084",
    "imdbID": "tt0074851",
    "Type": "movie",
    "DVD": "05 Jul 2000",
    "BoxOffice": "N/A",
    "Production": "Rialto Pictures",
    "Website": "N/A",
    "Response": "True"
}