{
    "Title": "Assault on Precinct 13",
    "Year": "1976",
    "Rated": "R",
    "Released": "12 Nov 1976",
    "Runtime": "91 min",
    "Genre": "Action, Crime, Thriller",
    "Director": "John Carpenter",
    "Writer": "John Carpenter",
    "Actors": "Austin Stoker, Darwin Joston, Laurie Zimmer, Martin West",
    "Plot": "An unlikely partnership between a Highway Patrol Officer, two criminals and a station secretary is formed to defend a defunct Los Angeles precinct office against a siege by a bloodthirsty street gang.",
    "Language": "English",
    "Country": "USA",
    "Awards": "1 nomination.",
    "Poster": "https://m.media-amazon.com/images/M/MV5BZTQzMTA2ZjItMDA2Mi00YTNjLWFkOTktYTk3Y2JhZTdiYzU5XkEyXkFqcGdeQXVyMTQxNzMzNDI@._V1_SX300.jpg",
    "Ratings": [
        {
            "Source": "Internet Movie Database",
            "Value": "7.4/10"
        },
        {
            "Source": "Rotten Tomatoes",
            "Value": "98%"
        },
        {
            "Source": "Metacritic",
            "Value": "89/100"
        }
    ],
    "Metascore": "89",
    "imdbRating": "7.4",
    "imdbVotes": "40,104",
    "imdbID": "tt0074156",
    "Type": "movie",
    "DVD": "11 Mar 2003",
    "BoxOffice": "N/A",
    "Production": "Turtle Releasing",
    "Website": "N/A",
    "Response": "True"
}