{
    "Title": "White Christmas",
    "Year": "1954",
    "Rated": "Not Rated",
    "Released": "15 Nov 1954",
    "Runtime": "120 min",
    "Genre": "Comedy, Musical, Romance",
    "Director": "Michael Curtiz",
    "Writer": "Norman Krasna (written for the screen by), Norman Panama (written for the screen by), Melvin Frank (written for the screen by)",
    "Actors": "Bing Crosby, Danny Kaye, Rosemary Clooney, Vera-Ellen",
    "Plot": "A successful song-and-dance team become romantically involved with a sister act and team up to save the failing Vermont inn of their former commanding general.",
    "Language": "English",
    "Country": "USA",
    "Awards": "N/A",
    "Poster": "https://m.media-amazon.com/images/M/MV5BYjI0ZTk0ZjQtZTMzOS00NDdmLTk0YzUtZTQ4NGRkNWFhZTkxXkEyXkFqcGdeQXVyNjc1NTYyMjg@._V1_SX300.jpg",
    "Ratings": [
        {
            "Source": "Internet Movie Database",
            "Value": "7.6/10"
        },
        {
            "Source": "Rotten Tomatoes",
            "Value": "76%"
        }
    ],
    "Metascore": "N/A",
    "imdbRating": "7.6",
    "imdbVotes": "28,641",
    "imdbID": "tt0047673",
    "Type": "movie",
    "DVD": "21 Nov 2000",
    "BoxOffice": "N/A",
    "Production": "Paramount Pictures",
    "Website": "N/A",
    "Response": "True"
}