{
    "Title": "Wuthering Heights",
    "Year": "1939",
    "Rated": "Not Rated",
    "Released": "07 Apr 1939",
    "Runtime": "104 min",
    "Genre": "Drama, Romance",
    "Director": "William Wyler",
    "Writer": "Charles MacArthur (screen play), Ben Hecht (screen play), Emily Bront\u00eb (from the novel by)",
    "Actors": "Merle Oberon, Laurence Olivier, David Niven, Flora Robson",
    "Plot": "A servant in the house of Wuthering Heights tells a traveller the unfortunate tale of lovers Cathy and Heathcliff.",
    "Language": "English",
    "Country": "USA",
    "Awards": "Won 1 Oscar. Another 5 wins & 7 nominations.",
    "Poster": "https://m.media-amazon.com/images/M/MV5BMDAxZDkzNTktYzQyMi00YmRlLWFmYWQtY2Q4ZTQyMGFlMzNmL2ltYWdlL2ltYWdlXkEyXkFqcGdeQXVyNjc1NTYyMjg@._V1_SX300.jpg",
    "Ratings": [
        {
            "Source": "Internet Movie Database",
            "Value": "7.6/10"
        },
        {
            "Source": "Rotten Tomatoes",
            "Value": "95%"
        }
    ],
    "Metascore": "N/A",
    "imdbRating": "7.6",
    "imdbVotes": "15,139",
    "imdbID": "tt0032145",
    "Type": "movie",
    "DVD": "28 Oct 1997",
    "BoxOffice": "N/A",
    "Production": "United Artists",
    "Website": "N/A",
    "Response": "True"
}