{
    "Title": "The Silence",
    "Year": "1963",
    "Rated": "R",
    "Released": "03 Feb 1964",
    "Runtime": "96 min",
    "Genre": "Drama",
    "Director": "Ingmar Bergman",
    "Writer": "Ingmar Bergman",
    "Actors": "Ingrid Thulin, Gunnel Lindblom, J\u00f6rgen Lindstr\u00f6m, H\u00e5kan Jahnberg",
    "Plot": "Two estranged sisters, Ester and Anna, and Anna's 10-year-old son travel to the Central European country on the verge of war. Ester becomes seriously ill and the three of them move into a hotel in a small town called Timoka.",
    "Language": "Swedish, English, German, French, Spanish",
    "Country": "Sweden",
    "Awards": "3 wins & 1 nomination.",
    "Poster": "https://m.media-amazon.com/images/M/MV5BZWJiYWYzZGEtYzc1OC00MjZiLWExMmUtMTcxNjE1MTgxMTFmL2ltYWdlL2ltYWdlXkEyXkFqcGdeQXVyMTAwNzgxMzQ@._V1_SX300.jpg",
    "Ratings": [
        {
            "Source": "Internet Movie Database",
            "Value": "7.9/10"
        },
        {
            "Source": "Rotten Tomatoes",
            "Value": "88%"
        }
    ],
    "Metascore": "N/A",
    "imdbRating": "7.9",
    "imdbVotes": "16,051",
    "imdbID": "tt0057611",
    "Type": "movie",
    "DVD": "19 Aug 2003",
    "BoxOffice": "N/A",
    "Production": "Criterion Collection",
    "Website": "N/A",
    "Response": "True"
}