{
    "Title": "DuckTales the Movie: Treasure of the Lost Lamp",
    "Year": "1990",
    "Rated": "G",
    "Released": "03 Aug 1990",
    "Runtime": "74 min",
    "Genre": "Animation, Adventure, Comedy, Family, Fantasy",
    "Director": "Bob Hathcock",
    "Writer": "Alan Burnett (animation screenplay)",
    "Actors": "Alan Young, Terence McGovern, Russi Taylor, Richard Libertini",
    "Plot": "Scrooge McDuck takes Huey, Dewey, and Louie to Egypt to find a pyramid and magic lamp.",
    "Language": "English",
    "Country": "France, USA",
    "Awards": "1 nomination.",
    "Poster": "https://m.media-amazon.com/images/M/MV5BMGY1NjdiMmItMmE5MS00NjllLWJmM2ItMmU1ZTRjMWYyZjc4XkEyXkFqcGdeQXVyMjA0MDQ0Mjc@._V1_SX300.jpg",
    "Ratings": [
        {
            "Source": "Internet Movie Database",
            "Value": "6.9/10"
        },
        {
            "Source": "Rotten Tomatoes",
            "Value": "88%"
        }
    ],
    "Metascore": "N/A",
    "imdbRating": "6.9",
    "imdbVotes": "23,613",
    "imdbID": "tt0099472",
    "Type": "movie",
    "DVD": "13 Nov 2007",
    "BoxOffice": "N/A",
    "Production": "Walt Disney Productions",
    "Website": "N/A",
    "Response": "True"
}