{
    "Title": "The Patriot",
    "Year": "2000",
    "Rated": "R",
    "Released": "28 Jun 2000",
    "Runtime": "165 min",
    "Genre": "Action, Drama, History, War",
    "Director": "Roland Emmerich",
    "Writer": "Robert Rodat",
    "Actors": "Mel Gibson, Heath Ledger, Joely Richardson, Jason Isaacs",
    "Plot": "Peaceful farmer Benjamin Martin is driven to lead the Colonial Militia during the American Revolution when a sadistic British officer murders his son.",
    "Language": "English",
    "Country": "USA, Germany",
    "Awards": "Nominated for 3 Oscars. Another 8 wins & 18 nominations.",
    "Poster": "https://m.media-amazon.com/images/M/MV5BMTkzMjE4ODU0MV5BMl5BanBnXkFtZTYwNTI2OTk2._V1_SX300.jpg",
    "Ratings": [
        {
            "Source": "Internet Movie Database",
            "Value": "7.2/10"
        },
        {
            "Source": "Rotten Tomatoes",
            "Value": "61%"
        },
        {
            "Source": "Metacritic",
            "Value": "63/100"
        }
    ],
    "Metascore": "63",
    "imdbRating": "7.2",
    "imdbVotes": "240,932",
    "imdbID": "tt0187393",
    "Type": "movie",
    "DVD": "25 Apr 2006",
    "BoxOffice": "$2,317,507",
    "Production": "Columbia Pictures",
    "Website": "N/A",
    "Response": "True"
}