{
    "Title": "Hot Shots!",
    "Year": "1991",
    "Rated": "PG-13",
    "Released": "31 Jul 1991",
    "Runtime": "84 min",
    "Genre": "Action, Comedy",
    "Director": "Jim Abrahams",
    "Writer": "Jim Abrahams, Pat Proft",
    "Actors": "Charlie Sheen, Cary Elwes, Valeria Golino, Lloyd Bridges",
    "Plot": "A parody of Top Gun (1986) in which a talented but unstable fighter pilot must overcome the ghosts of his father and save a mission sabotaged by greedy weapons manufacturers.",
    "Language": "English",
    "Country": "USA",
    "Awards": "1 win.",
    "Poster": "https://m.media-amazon.com/images/M/MV5BNzgxNmI1ODItZWZlYy00ZjE0LWIwYjgtMTk2MzU0MjhkOWIzXkEyXkFqcGdeQXVyMTQxNzMzNDI@._V1_SX300.jpg",
    "Ratings": [
        {
            "Source": "Internet Movie Database",
            "Value": "6.8/10"
        },
        {
            "Source": "Rotten Tomatoes",
            "Value": "83%"
        },
        {
            "Source": "Metacritic",
            "Value": "61/100"
        }
    ],
    "Metascore": "61",
    "imdbRating": "6.8",
    "imdbVotes": "93,036",
    "imdbID": "tt0102059",
    "Type": "movie",
    "DVD": "06 Aug 2002",
    "BoxOffice": "N/A",
    "Production": "Twentieth Century Fox Home Entertainment",
    "Website": "N/A",
    "Response": "True"
}