{
    "Title": "Heartless",
    "Year": "1997",
    "Rated": "N/A",
    "Released": "05 Nov 1997",
    "Runtime": "105 min",
    "Genre": "Thriller",
    "Director": "Judith Vogelsang",
    "Writer": "Leslie Lehr",
    "Actors": "M\u00e4dchen Amick, David Packer, Tom Schanley, Louise Fletcher",
    "Plot": "A shy young woman receives a heart transplant and undergoes a personality change that may be connected to the murdered donor.",
    "Language": "English",
    "Country": "USA",
    "Awards": "N/A",
    "Poster": "https://m.media-amazon.com/images/M/MV5BMTY4ODgwNTM2M15BMl5BanBnXkFtZTcwODMxODEyMQ@@._V1_SX300.jpg",
    "Ratings": [
        {
            "Source": "Internet Movie Database",
            "Value": "4.8/10"
        }
    ],
    "Metascore": "N/A",
    "imdbRating": "4.8",
    "imdbVotes": "129",
    "imdbID": "tt0119268",
    "Type": "movie",
    "DVD": "19 Sep 2000",
    "BoxOffice": "N/A",
    "Production": "Leo Films",
    "Website": "N/A",
    "Response": "True"
}