{
    "Title": "Teenage Mutant Ninja Turtles II: The Secret of the Ooze",
    "Year": "1991",
    "Rated": "PG",
    "Released": "22 Mar 1991",
    "Runtime": "88 min",
    "Genre": "Action, Adventure, Comedy, Family, Sci-Fi",
    "Director": "Michael Pressman",
    "Writer": "Kevin Eastman (based on characters created by), Peter Laird (based on characters created by), Todd W. Langen",
    "Actors": "Paige Turco, David Warner, Michelan Sisti, Leif Tilden",
    "Plot": "The Turtles and the Shredder battle once again, this time for the last canister of the ooze that created the Turtles, with which Shredder wants to unleash an army of new mutants.",
    "Language": "English",
    "Country": "USA, Hong Kong",
    "Awards": "3 wins & 1 nomination.",
    "Poster": "https://m.media-amazon.com/images/M/MV5BODdkMTk5ODMtYjhkMS00MGNlLThkMmItYjRjMTc2ZWY1OWIxXkEyXkFqcGdeQXVyNTAyODkwOQ@@._V1_SX300.jpg",
    "Ratings": [
        {
            "Source": "Internet Movie Database",
            "Value": "6.0/10"
        },
        {
            "Source": "Rotten Tomatoes",
            "Value": "35%"
        },
        {
            "Source": "Metacritic",
            "Value": "45/100"
        }
    ],
    "Metascore": "45",
    "imdbRating": "6.0",
    "imdbVotes": "48,428",
    "imdbID": "tt0103060",
    "Type": "movie",
    "DVD": "03 Sep 2002",
    "BoxOffice": "N/A",
    "Production": "WARNER BROTHERS PICTURES",
    "Website": "N/A",
    "Response": "True"
}