{
    "Title": "The Good Son",
    "Year": "1993",
    "Rated": "R",
    "Released": "24 Sep 1993",
    "Runtime": "87 min",
    "Genre": "Drama, Thriller",
    "Director": "Joseph Ruben",
    "Writer": "Ian McEwan",
    "Actors": "Macaulay Culkin, Elijah Wood, Wendy Crewson, David Morse",
    "Plot": "A young boy stays with his aunt and uncle and befriends his cousin, a boy of the same age who begins showing increasing signs of violent and psychopathic behavior.",
    "Language": "English",
    "Country": "USA",
    "Awards": "1 win & 2 nominations.",
    "Poster": "https://m.media-amazon.com/images/M/MV5BZDBiOWM2ZGEtNTNjNi00NmY1LWJhOTEtNjQ5MmNiMTgzNWVjL2ltYWdlXkEyXkFqcGdeQXVyMTQxNzMzNDI@._V1_SX300.jpg",
    "Ratings": [
        {
            "Source": "Internet Movie Database",
            "Value": "6.4/10"
        },
        {
            "Source": "Rotten Tomatoes",
            "Value": "26%"
        }
    ],
    "Metascore": "N/A",
    "imdbRating": "6.4",
    "imdbVotes": "34,280",
    "imdbID": "tt0107034",
    "Type": "movie",
    "DVD": "03 Feb 2004",
    "BoxOffice": "N/A",
    "Production": "Twentieth Century Fox Home Entertainment",
    "Website": "N/A",
    "Response": "True"
}