{
    "Title": "Farewell My Concubine",
    "Year": "1993",
    "Rated": "R",
    "Released": "15 Oct 1993",
    "Runtime": "171 min",
    "Genre": "Drama, Music, Romance",
    "Director": "Kaige Chen",
    "Writer": "Pik Wah Lee (novel), Pik Wah Lee (screenplay), Wei Lu",
    "Actors": "Leslie Cheung, Fengyi Zhang, Li Gong, Qi L\u00fc",
    "Plot": "The story of two men, who met as apprentices in the Peking Opera, and stayed friends for over 50 years.",
    "Language": "Mandarin",
    "Country": "China, Hong Kong",
    "Awards": "Nominated for 2 Oscars. Another 18 wins & 7 nominations.",
    "Poster": "https://m.media-amazon.com/images/M/MV5BYmFhZmM3Y2MtNDA1Ny00NjkzLWJkM2EtYWU1ZjEwYmNjZDQ0XkEyXkFqcGdeQXVyMTMxMTY0OTQ@._V1_SX300.jpg",
    "Ratings": [
        {
            "Source": "Internet Movie Database",
            "Value": "8.1/10"
        },
        {
            "Source": "Rotten Tomatoes",
            "Value": "86%"
        }
    ],
    "Metascore": "N/A",
    "imdbRating": "8.1",
    "imdbVotes": "22,616",
    "imdbID": "tt0106332",
    "Type": "movie",
    "DVD": "14 Dec 1999",
    "BoxOffice": "N/A",
    "Production": "Miramax",
    "Website": "N/A",
    "Response": "True"
}