{
    "Title": "Regarding Henry",
    "Year": "1991",
    "Rated": "PG-13",
    "Released": "10 Jul 1991",
    "Runtime": "108 min",
    "Genre": "Drama, Romance",
    "Director": "Mike Nichols",
    "Writer": "J.J. Abrams",
    "Actors": "Harrison Ford, Annette Bening, Michael Haley, Stanley Swerdlow",
    "Plot": "After being shot, a man loses his memory and must relearn speech and mobility, but he has a loving family to support him.",
    "Language": "English",
    "Country": "USA",
    "Awards": "1 win & 2 nominations.",
    "Poster": "https://m.media-amazon.com/images/M/MV5BMDU0YzM4MzAtZTNmNi00Yzc4LTliNTgtYzFmZmEzNmM4MmRmXkEyXkFqcGdeQXVyNjUwNzk3NDc@._V1_SX300.jpg",
    "Ratings": [
        {
            "Source": "Internet Movie Database",
            "Value": "6.7/10"
        },
        {
            "Source": "Rotten Tomatoes",
            "Value": "43%"
        },
        {
            "Source": "Metacritic",
            "Value": "47/100"
        }
    ],
    "Metascore": "47",
    "imdbRating": "6.7",
    "imdbVotes": "27,755",
    "imdbID": "tt0102768",
    "Type": "movie",
    "DVD": "09 Sep 2003",
    "BoxOffice": "N/A",
    "Production": "Paramount Home Video",
    "Website": "N/A",
    "Response": "True"
}