{
    "Title": "Storytelling",
    "Year": "2001",
    "Rated": "R",
    "Released": "08 Nov 2001",
    "Runtime": "87 min",
    "Genre": "Comedy, Drama, Romance",
    "Director": "Todd Solondz",
    "Writer": "Todd Solondz",
    "Actors": "Selma Blair, Leo Fitzpatrick, Robert Wisdom, Maria Thayer",
    "Plot": "College and high school serve as the backdrop for two stories about dysfunction and personal turmoil.",
    "Language": "English, Spanish",
    "Country": "USA",
    "Awards": "1 nomination.",
    "Poster": "https://m.media-amazon.com/images/M/MV5BNjYzNGIyNzUtNzAxZi00NzFhLTg3MDktMzljOGVmMDllNDg0XkEyXkFqcGdeQXVyMTQxNzMzNDI@._V1_SX300.jpg",
    "Ratings": [
        {
            "Source": "Internet Movie Database",
            "Value": "6.8/10"
        },
        {
            "Source": "Rotten Tomatoes",
            "Value": "53%"
        },
        {
            "Source": "Metacritic",
            "Value": "50/100"
        }
    ],
    "Metascore": "50",
    "imdbRating": "6.8",
    "imdbVotes": "16,540",
    "imdbID": "tt0250081",
    "Type": "movie",
    "DVD": "16 Jul 2002",
    "BoxOffice": "$850,758",
    "Production": "Fine Line Features",
    "Website": "N/A",
    "Response": "True"
}