{
    "Title": "L'auberge espagnole",
    "Year": "2002",
    "Rated": "R",
    "Released": "20 Jun 2003",
    "Runtime": "122 min",
    "Genre": "Comedy, Drama, Romance",
    "Director": "C\u00e9dric Klapisch",
    "Writer": "C\u00e9dric Klapisch",
    "Actors": "Romain Duris, Judith Godr\u00e8che, Audrey Tautou, C\u00e9cile de France",
    "Plot": "A strait-laced French student moves into an apartment in Barcelona with a cast of six other characters from all over Europe. Together, they speak the international language of love and friendship.",
    "Language": "French, Spanish, English, Catalan, Danish, German, Italian",
    "Country": "France, Spain",
    "Awards": "8 wins & 9 nominations.",
    "Poster": "https://m.media-amazon.com/images/M/MV5BYzZkMWY5M2ItOTA1Yi00MWQ0LWE4OTgtNWY1YmE0NjQyOTdlXkEyXkFqcGdeQXVyMjc4MjcxNzI@._V1_SX300.jpg",
    "Ratings": [
        {
            "Source": "Internet Movie Database",
            "Value": "7.3/10"
        },
        {
            "Source": "Rotten Tomatoes",
            "Value": "76%"
        },
        {
            "Source": "Metacritic",
            "Value": "65/100"
        }
    ],
    "Metascore": "65",
    "imdbRating": "7.3",
    "imdbVotes": "37,933",
    "imdbID": "tt0283900",
    "Type": "movie",
    "DVD": "23 Dec 2003",
    "BoxOffice": "$3,752,818",
    "Production": "Fox Searchlight Pictures",
    "Website": "N/A",
    "Response": "True"
}