{
    "Title": "Coffee and Cigarettes",
    "Year": "2003",
    "Rated": "R",
    "Released": "11 Jun 2004",
    "Runtime": "95 min",
    "Genre": "Comedy, Drama, Music",
    "Director": "Jim Jarmusch",
    "Writer": "Jim Jarmusch",
    "Actors": "Roberto Benigni, Steven Wright, Joie Lee, Cinqu\u00e9 Lee",
    "Plot": "A series of vignettes that all have coffee and cigarettes in common.",
    "Language": "English, French",
    "Country": "USA, Japan, Italy",
    "Awards": "2 wins & 9 nominations.",
    "Poster": "https://m.media-amazon.com/images/M/MV5BYzQxNzMzZTEtNjc1YS00NzExLWI0ZGItMWMxZTQzNDI1MjQ3XkEyXkFqcGdeQXVyMTQxNzMzNDI@._V1_SX300.jpg",
    "Ratings": [
        {
            "Source": "Internet Movie Database",
            "Value": "7.1/10"
        },
        {
            "Source": "Rotten Tomatoes",
            "Value": "64%"
        },
        {
            "Source": "Metacritic",
            "Value": "65/100"
        }
    ],
    "Metascore": "65",
    "imdbRating": "7.1",
    "imdbVotes": "56,186",
    "imdbID": "tt0379217",
    "Type": "movie",
    "DVD": "21 Sep 2004",
    "BoxOffice": "$1,971,135",
    "Production": "MGM",
    "Website": "N/A",
    "Response": "True"
}