{
    "Title": "The Italian Job",
    "Year": "2003",
    "Rated": "PG-13",
    "Released": "30 May 2003",
    "Runtime": "111 min",
    "Genre": "Action, Crime, Thriller",
    "Director": "F. Gary Gray",
    "Writer": "Troy Kennedy-Martin, Donna Powers (screenplay), Wayne Powers (screenplay)",
    "Actors": "Mark Wahlberg, Charlize Theron, Donald Sutherland, Jason Statham",
    "Plot": "After being betrayed and left for dead in Italy, Charlie Croker and his team plan an elaborate gold heist against their former ally.",
    "Language": "English, Russian, Italian",
    "Country": "USA, France, UK, Italy",
    "Awards": "8 wins & 7 nominations.",
    "Poster": "https://m.media-amazon.com/images/M/MV5BNDYyNzYxNjYtNmYzMC00MTE0LWIwMmYtNTAyZDBjYTIxMTRhXkEyXkFqcGdeQXVyNDk3NzU2MTQ@._V1_SX300.jpg",
    "Ratings": [
        {
            "Source": "Internet Movie Database",
            "Value": "7.0/10"
        },
        {
            "Source": "Rotten Tomatoes",
            "Value": "73%"
        },
        {
            "Source": "Metacritic",
            "Value": "68/100"
        }
    ],
    "Metascore": "68",
    "imdbRating": "7.0",
    "imdbVotes": "325,897",
    "imdbID": "tt0317740",
    "Type": "movie",
    "DVD": "07 Oct 2003",
    "BoxOffice": "$105,996,316",
    "Production": "Paramount Pictures",
    "Website": "N/A",
    "Response": "True"
}