{
    "Title": "Inspector Gadget 2",
    "Year": "2003",
    "Rated": "G",
    "Released": "11 Mar 2003",
    "Runtime": "89 min",
    "Genre": "Action, Comedy, Crime, Family, Sci-Fi",
    "Director": "Alex Zamm",
    "Writer": "Andy Heyward (characters), Jean Chalopin (characters), Bruno Bianchi (characters), Ron Anderson, William Robertson, Alex Zamm",
    "Actors": "French Stewart, Elaine Hendrix, Tony Martin, Caitlin Wachs",
    "Plot": "Inspector Gadget returns in this sequel to his 1999 hit; a glitched Gadget once again has to fight his arch nemesis, Claw, with the aid of a female Gadget: G2.",
    "Language": "English",
    "Country": "USA",
    "Awards": "4 nominations.",
    "Poster": "https://m.media-amazon.com/images/M/MV5BMTU1MjkxODEwNl5BMl5BanBnXkFtZTYwOTM4NDg2._V1_SX300.jpg",
    "Ratings": [
        {
            "Source": "Internet Movie Database",
            "Value": "3.4/10"
        },
        {
            "Source": "Rotten Tomatoes",
            "Value": "40%"
        }
    ],
    "Metascore": "N/A",
    "imdbRating": "3.4",
    "imdbVotes": "5,199",
    "imdbID": "tt0301454",
    "Type": "movie",
    "DVD": "11 Mar 2003",
    "BoxOffice": "N/A",
    "Production": "Walt Disney Pictures",
    "Website": "N/A",
    "Response": "True"
}