{
    "Title": "Chapter 27",
    "Year": "2007",
    "Rated": "R",
    "Released": "15 Dec 2007",
    "Runtime": "84 min",
    "Genre": "Biography, Crime, Drama, History",
    "Director": "J.P. Schaefer",
    "Writer": "J.P. Schaefer, Jack Jones (inspired by the book \"Let Me Take You Down\")",
    "Actors": "Chuck Cooper, Victor Verhaeghe, Robert Gerard Larkin, Lindsay Lohan",
    "Plot": "A film about Mark David Chapman in the days leading up to the infamous murder of Beatle John Lennon.",
    "Language": "English",
    "Country": "Canada, USA",
    "Awards": "2 wins.",
    "Poster": "https://m.media-amazon.com/images/M/MV5BMzY0YmRhZDYtN2U3NS00ZTczLTg3MTQtZjYxNzQwOTdiZGM3XkEyXkFqcGdeQXVyNTM0NTU5Mg@@._V1_SX300.jpg",
    "Ratings": [
        {
            "Source": "Internet Movie Database",
            "Value": "5.7/10"
        },
        {
            "Source": "Rotten Tomatoes",
            "Value": "18%"
        },
        {
            "Source": "Metacritic",
            "Value": "32/100"
        }
    ],
    "Metascore": "32",
    "imdbRating": "5.7",
    "imdbVotes": "9,863",
    "imdbID": "tt0488988",
    "Type": "movie",
    "DVD": "30 Sep 2008",
    "BoxOffice": "N/A",
    "Production": "Vitagraph Films",
    "Website": "N/A",
    "Response": "True"
}