{
    "Title": "Veer-Zaara",
    "Year": "2004",
    "Rated": "Not Rated",
    "Released": "12 Nov 2004",
    "Runtime": "192 min",
    "Genre": "Drama, Family, Musical, Romance",
    "Director": "Yash Chopra",
    "Writer": "Aditya Chopra (dialogue), Aditya Chopra (screenplay), Aditya Chopra (story)",
    "Actors": "Shah Rukh Khan, Rani Mukerji, Preity Zinta, Kiron Kher",
    "Plot": "Veer-Zaara is a saga of love, separation, courage and sacrifice. A love story that is an inspiration and will remain a legend forever.",
    "Language": "Hindi, Urdu, Punjabi",
    "Country": "India",
    "Awards": "21 wins & 29 nominations.",
    "Poster": "https://m.media-amazon.com/images/M/MV5BMTI1Njc3ODg1Ml5BMl5BanBnXkFtZTcwNDYxNDcyMQ@@._V1_SX300.jpg",
    "Ratings": [
        {
            "Source": "Internet Movie Database",
            "Value": "7.8/10"
        },
        {
            "Source": "Rotten Tomatoes",
            "Value": "92%"
        },
        {
            "Source": "Metacritic",
            "Value": "67/100"
        }
    ],
    "Metascore": "67",
    "imdbRating": "7.8",
    "imdbVotes": "45,660",
    "imdbID": "tt0420332",
    "Type": "movie",
    "DVD": "26 Feb 2005",
    "BoxOffice": "$2,856,738",
    "Production": "Yash Raj Films Pvt. Ltd.",
    "Website": "N/A",
    "Response": "True"
}