{
    "Title": "Persepolis",
    "Year": "2007",
    "Rated": "PG-13",
    "Released": "22 Feb 2008",
    "Runtime": "96 min",
    "Genre": "Animation, Biography, Drama, History, War",
    "Director": "Vincent Paronnaud, Marjane Satrapi",
    "Writer": "Marjane Satrapi (comic), Vincent Paronnaud (scenario)",
    "Actors": "Chiara Mastroianni, Danielle Darrieux, Catherine Deneuve, Simon Abkarian",
    "Plot": "A precocious and outspoken Iranian girl grows up during the Islamic Revolution.",
    "Language": "French, English, Persian, German",
    "Country": "France, USA",
    "Awards": "Nominated for 1 Oscar. Another 28 wins & 54 nominations.",
    "Poster": "https://m.media-amazon.com/images/M/MV5BMGRkZThmYzEtYjQxZC00OWEzLThjYjAtYzFkMjY0NGZkZWI4XkEyXkFqcGdeQXVyNTAyODkwOQ@@._V1_SX300.jpg",
    "Ratings": [
        {
            "Source": "Internet Movie Database",
            "Value": "8.0/10"
        },
        {
            "Source": "Rotten Tomatoes",
            "Value": "96%"
        },
        {
            "Source": "Metacritic",
            "Value": "90/100"
        }
    ],
    "Metascore": "90",
    "imdbRating": "8.0",
    "imdbVotes": "83,040",
    "imdbID": "tt0808417",
    "Type": "movie",
    "DVD": "24 Jun 2008",
    "BoxOffice": "$4,400,000",
    "Production": "Sony Pictures Classics",
    "Website": "N/A",
    "Response": "True"
}