{
    "Title": "Pok\u00e9mon: Lucario and the Mystery of Mew",
    "Year": "2005",
    "Rated": "Unrated",
    "Released": "19 Sep 2006",
    "Runtime": "103 min",
    "Genre": "Animation, Action, Adventure, Family, Fantasy, Sci-Fi",
    "Director": "Kunihiko Yuyama, Darren Dunstan",
    "Writer": "Kathy Pilon, Hideki Sonoda, John Touhey",
    "Actors": "Veronica Taylor, Eric Stuart, Amy Birnbaum, Madeleine Blaustein",
    "Plot": "When Pikachu is taken to the Tree of Beginnings by the playful Mew, Ash Ketchum and friends are guided to the tree by Lucario, a time-displaced Pok\u00e9mon who seeks answers regarding the betrayal of his master.",
    "Language": "Japanese, English",
    "Country": "Japan",
    "Awards": "N/A",
    "Poster": "https://m.media-amazon.com/images/M/MV5BMTUxOTcwNjAwMl5BMl5BanBnXkFtZTgwMjc2MzQ2NjE@._V1_SX300.jpg",
    "Ratings": [
        {
            "Source": "Internet Movie Database",
            "Value": "6.9/10"
        }
    ],
    "Metascore": "N/A",
    "imdbRating": "6.9",
    "imdbVotes": "3,525",
    "imdbID": "tt0875609",
    "Type": "movie",
    "DVD": "19 Sep 2006",
    "BoxOffice": "N/A",
    "Production": "4 Kids Entertainment",
    "Website": "N/A",
    "Response": "True"
}