{
    "Title": "Detective Conan: The Last Wizard of the Century",
    "Year": "1999",
    "Rated": "N/A",
    "Released": "17 Apr 1999",
    "Runtime": "100 min",
    "Genre": "Animation, Adventure, Crime",
    "Director": "Kenji Kodama, Yasuichir\u00f4 Yamamoto",
    "Writer": "Gosho Aoyama (manga), Kazunari Furuuchi (screenplay), Eric Vale (script writer), Eric Vale (head writer)",
    "Actors": "Laura Bailey, Chaf\u00fbrin, Colleen Clinkenbeard, Kevin Connolly",
    "Plot": "Suzuki Zaibatsu found the 51st Easter Egg made by Russian Jewel maker February. Kaido Kido sent police a warning letter that he would stole the egg which Suzuki would display 4 days later. ...",
    "Language": "Japanese, Italian",
    "Country": "Japan",
    "Awards": "N/A",
    "Poster": "https://m.media-amazon.com/images/M/MV5BYjZjNmNmNDMtYTI2MC00N2QyLWI3NDctOWQ5NmQ4OTQxMWJmXkEyXkFqcGdeQXVyNjUwMTQ4NjE@._V1_SX300.jpg",
    "Ratings": [
        {
            "Source": "Internet Movie Database",
            "Value": "7.5/10"
        }
    ],
    "Metascore": "N/A",
    "imdbRating": "7.5",
    "imdbVotes": "1,287",
    "imdbID": "tt1067920",
    "Type": "movie",
    "DVD": "15 Dec 2009",
    "BoxOffice": "N/A",
    "Production": "N/A",
    "Website": "N/A",
    "Response": "True"
}