{
    "Title": "Charlie Countryman",
    "Year": "2013",
    "Rated": "R",
    "Released": "13 Sep 2013",
    "Runtime": "103 min",
    "Genre": "Comedy, Drama, Romance, Thriller",
    "Director": "Fredrik Bond",
    "Writer": "Matt Drake",
    "Actors": "Shia LaBeouf, Evan Rachel Wood, Mads Mikkelsen, Til Schweiger",
    "Plot": "While travelling abroad, a guy falls for a Romanian beauty whose unreachable heart has its origins in her violent, charismatic ex.",
    "Language": "English, Romanian",
    "Country": "USA, Romania",
    "Awards": "1 nomination.",
    "Poster": "https://m.media-amazon.com/images/M/MV5BMjA3MTcyNjk3NF5BMl5BanBnXkFtZTgwNjkzNzUzMDE@._V1_SX300.jpg",
    "Ratings": [
        {
            "Source": "Internet Movie Database",
            "Value": "6.4/10"
        },
        {
            "Source": "Rotten Tomatoes",
            "Value": "27%"
        },
        {
            "Source": "Metacritic",
            "Value": "31/100"
        }
    ],
    "Metascore": "31",
    "imdbRating": "6.4",
    "imdbVotes": "25,728",
    "imdbID": "tt1196948",
    "Type": "movie",
    "DVD": "21 Jan 2014",
    "BoxOffice": "N/A",
    "Production": "Millennium Entertainment",
    "Website": "N/A",
    "Response": "True"
}