{
    "Title": "Dragon",
    "Year": "2011",
    "Rated": "R",
    "Released": "04 Jul 2011",
    "Runtime": "98 min",
    "Genre": "Action, Crime, Drama, Thriller",
    "Director": "Peter Ho-Sun Chan",
    "Writer": "Oi Wah Lam, Joyce Chan",
    "Actors": "Donnie Yen, Wei Tang, Jia-Min Li, Wei Zheng",
    "Plot": "A papermaker gets involved with a murder case concerning two criminals leading to a determined detective suspecting him and the former's vicious father searching for him",
    "Language": "Mandarin",
    "Country": "Hong Kong, China",
    "Awards": "11 wins & 17 nominations.",
    "Poster": "https://m.media-amazon.com/images/M/MV5BMTc4OTUxMDQ1NF5BMl5BanBnXkFtZTcwOTczMDI2OA@@._V1_SX300.jpg",
    "Ratings": [
        {
            "Source": "Internet Movie Database",
            "Value": "7.1/10"
        },
        {
            "Source": "Rotten Tomatoes",
            "Value": "85%"
        },
        {
            "Source": "Metacritic",
            "Value": "62/100"
        }
    ],
    "Metascore": "62",
    "imdbRating": "7.1",
    "imdbVotes": "13,031",
    "imdbID": "tt1718199",
    "Type": "movie",
    "DVD": "16 Apr 2013",
    "BoxOffice": "$11,137",
    "Production": "Radius/The Weinstein Co.",
    "Website": "N/A",
    "Response": "True"
}