{
    "Title": "Boo! A Madea Halloween",
    "Year": "2016",
    "Rated": "PG-13",
    "Released": "21 Oct 2016",
    "Runtime": "103 min",
    "Genre": "Comedy, Drama, Horror",
    "Director": "Tyler Perry",
    "Writer": "Tyler Perry",
    "Actors": "Tyler Perry, Cassi Davis, Patrice Lovely, Bella Thorne",
    "Plot": "Madea winds up in the middle of mayhem when she spends a haunted Halloween fending off killers, paranormal poltergeists, ghosts, ghouls and zombies while keeping a watchful eye on a group of misbehaving teens.",
    "Language": "English",
    "Country": "Hong Kong, USA",
    "Awards": "5 nominations.",
    "Poster": "https://m.media-amazon.com/images/M/MV5BMTUxNTE2MTM0NF5BMl5BanBnXkFtZTgwNjE5MTIxMDI@._V1_SX300.jpg",
    "Ratings": [
        {
            "Source": "Internet Movie Database",
            "Value": "4.6/10"
        },
        {
            "Source": "Rotten Tomatoes",
            "Value": "19%"
        },
        {
            "Source": "Metacritic",
            "Value": "30/100"
        }
    ],
    "Metascore": "30",
    "imdbRating": "4.6",
    "imdbVotes": "7,043",
    "imdbID": "tt5325452",
    "Type": "movie",
    "DVD": "31 Jan 2017",
    "BoxOffice": "$73,159,525",
    "Production": "Lionsgate",
    "Website": "N/A",
    "Response": "True"
}