{
    "Title": "Looking for Teddy",
    "Year": "2018",
    "Rated": "N/A",
    "Released": "20 Jun 2018",
    "Runtime": "82 min",
    "Genre": "Comedy",
    "Director": "Julien Herv\u00e9, Philippe Mechelen",
    "Writer": "Nessim Chikhaoui (collaboration), Julien Herv\u00e9 (screenplay), Philippe Mechelen (screenplay)",
    "Actors": "Kad Merad, Malik Bentalha, Romain Lancry, David Salles",
    "Plot": "A father enlists the help of an airport employee on a quest to find his daughter's teddy.",
    "Language": "French",
    "Country": "France",
    "Awards": "N/A",
    "Poster": "https://m.media-amazon.com/images/M/MV5BNGZmN2YzOTEtMmZhYS00ODJlLWJiOWMtOWZlNjZlNGZkMjM1XkEyXkFqcGdeQXVyMjU3Nzg4MDk@._V1_SX300.jpg",
    "Ratings": [
        {
            "Source": "Internet Movie Database",
            "Value": "5.2/10"
        }
    ],
    "Metascore": "N/A",
    "imdbRating": "5.2",
    "imdbVotes": "378",
    "imdbID": "tt6832138",
    "Type": "movie",
    "DVD": "N/A",
    "BoxOffice": "N/A",
    "Production": "N/A",
    "Website": "N/A",
    "Response": "True"
}