{
    "Title": "Old Suffolk Boys",
    "Year": "2019",
    "Rated": "N/A",
    "Released": "N/A",
    "Runtime": "20 min",
    "Genre": "Documentary, Short",
    "Director": "Florian Kotulla",
    "Writer": "N/A",
    "Actors": "N/A",
    "Plot": "John Holder returns to the village he grew up, Badwell Ash, reconnecting with family and friends from the past and encountering stories - of growing up and growing old in Suffolk, as well ...",
    "Language": "English",
    "Country": "UK",
    "Awards": "N/A",
    "Poster": "https://m.media-amazon.com/images/M/MV5BOWE1MTE5YTMtOGE2OC00YThlLWIxZjgtNTdlYTYzNDZlM2Y3XkEyXkFqcGdeQXVyNjg3MDQwNzk@._V1_SX300.jpg",
    "Ratings": [],
    "Metascore": "N/A",
    "imdbRating": "N/A",
    "imdbVotes": "N/A",
    "imdbID": "tt9105682",
    "Type": "movie",
    "DVD": "N/A",
    "BoxOffice": "N/A",
    "Production": "N/A",
    "Website": "N/A",
    "Response": "True"
}